PlavchanPeriodogram/Plavchan_Periodogram.py
PlavchanPeriodogram/__init__.py
PlavchanPeriodogram-0.0.7.dist-info/LICENSE.txt
PlavchanPeriodogram-0.0.7.dist-info/METADATA
PlavchanPeriodogram-0.0.7.dist-info/WHEEL
PlavchanPeriodogram-0.0.7.dist-info/top_level.txt
PlavchanPeriodogram-0.0.7.dist-info/RECORD
