Metadata-Version: 2.1
Name: PlavchanPeriodogram
Version: 0.0.7
Summary: It can calculate Plavchan Periodogram
Home-page: https://github.com/masuta16/PlavchanPeriodogram
Author: Israel Andrade
Author-email: israndade16@hotmail.com
License: MIT License
Keywords: Plavchan Periodogram
License-File: LICENSE.txt
Requires-Dist: numpy
Requires-Dist: lightkurve
Requires-Dist: matplotlib
